[{"centerlat":"28.200000","centerlng":"144.400000","endtime":"2007\/11\/13 2:00:00","enname":"TAPAH","isactive":"0","land":[],"name":"塔巴","points":[{"forecast":[],"lat":"22.30","lng":"142.30","movedirection":"","movespeed":"","power":"8","pressure":"996","radius10":"","radius7":"160","speed":"18","strong":"热带风暴","time":"2007\/11\/12 8:00:00"},{"forecast":[],"lat":"23.10","lng":"143.40","movedirection":"","movespeed":"","power":"8","pressure":"996","radius10":"","radius7":"180","speed":"18","strong":"热带风暴","time":"2007\/11\/12 14:00:00"},{"forecast":[],"lat":"24.00","lng":"144.70","movedirection":"东北东","movespeed":"30","power":"8","pressure":"998","radius10":"","radius7":"180","speed":"18","strong":"热带风暴","time":"2007\/11\/12 20:00:00"},{"forecast":[],"lat":"24.10","lng":"146.50","movedirection":"","movespeed":"","power":"8","pressure":"998","radius10":"","radius7":"180","speed":"18","strong":"热带风暴","time":"2007\/11\/13 2:00:00"}],"starttime":"2007\/11\/12 8:00:00","tfid":"200723","warnlevel":"2"}]
