[{"centerlat":"35.250000","centerlng":"143.400000","endtime":"2004\/8\/31 20:00:00","enname":"CHABA","isactive":"0","land":[],"name":"暹芭","points":[{"forecast":[],"lat":"13.80","lng":"157.00","movedirection":"西","movespeed":"20","power":"8","pressure":"990","radius10":"","radius7":"100","speed":"20","strong":"热带风暴","time":"2004\/8\/20 14:00:00"},{"forecast":[],"lat":"14.10","lng":"156.90","movedirection":"北北西","movespeed":"15","power":"9","pressure":"990","radius10":"","radius7":"330","speed":"23","strong":"热带风暴","time":"2004\/8\/20 15:00:00"},{"forecast":[],"lat":"14.20","lng":"156.20","movedirection":"西北西","movespeed":"20","power":"9","pressure":"990","radius10":"","radius7":"330","speed":"23","strong":"热带风暴","time":"2004\/8\/20 18:00:00"},{"forecast":[],"lat":"14.20","lng":"155.50","movedirection":"","movespeed":"","power":"9","pressure":"","radius10":"","radius7":"","speed":"23","strong":"热带风暴","time":"2004\/8\/20 20:00:00"},{"forecast":[],"lat":"14.40","lng":"155.40","movedirection":"西","movespeed":"25","power":"10","pressure":"985","radius10":"","radius7":"370","speed":"25","strong":"强热带风暴","time":"2004\/8\/20 21:00:00"},{"forecast":[],"lat":"14.50","lng":"154.60","movedirection":"西","movespeed":"30","power":"10","pressure":"985","radius10":"","radius7":"370","speed":"25","strong":"强热带风暴","time":"2004\/8\/21 0:00:00"},{"forecast":[],"lat":"14.60","lng":"154.30","movedirection":"","movespeed":"20","power":"10","pressure":"985","radius10":"","radius7":"150","speed":"25","strong":"强热带风暴","time":"2004\/8\/21 2:00:00"},{"forecast":[],"lat":"14.50","lng":"154.20","movedirection":"西","movespeed":"20","power":"10","pressure":"985","radius10":"","radius7":"370","speed":"25","strong":"强热带风暴","time":"2004\/8\/21 3:00:00"},{"forecast":[],"lat":"14.50","lng":"153.70","movedirection":"西","movespeed":"15","power":"10","pressure":"985","radius10":"","radius7":"370","speed":"25","strong":"强热带风暴","time":"2004\/8\/21 6:00:00"},{"forecast":[],"lat":"14.40","lng":"152.80","movedirection":"","movespeed":"22","power":"10","pressure":"985","radius10":"","radius7":"150","speed":"25","strong":"强热带风暴","time":"2004\/8\/21 8:00:00"},{"forecast":[],"lat":"14.50","lng":"152.80","movedirection":"西","movespeed":"25","power":"10","pressure":"985","radius10":"","radius7":"410","speed":"25","strong":"强热带风暴","time":"2004\/8\/21 9:00:00"},{"forecast":[],"lat":"14.50","lng":"152.30","movedirection":"西","movespeed":"25","power":"10","pressure":"985","radius10":"","radius7":"410","speed":"25","strong":"强热带风暴","time":"2004\/8\/21 12:00:00"},{"forecast":[],"lat":"14.40","lng":"151.80","movedirection":"","movespeed":"21","power":"10","pressure":"980","radius10":"50","radius7":"150","speed":"28","strong":"强热带风暴","time":"2004\/8\/21 14:00:00"},{"forecast":[],"lat":"14.50","lng":"151.80","movedirection":"西","movespeed":"15","power":"10","pressure":"985","radius10":"","radius7":"410","speed":"25","strong":"强热带风暴","time":"2004\/8\/21 15:00:00"},{"forecast":[],"lat":"14.20","lng":"150.80","movedirection":"西","movespeed":"20","power":"10","pressure":"985","radius10":"","radius7":"410","speed":"25","strong":"强热带风暴","time":"2004\/8\/21 18:00:00"},{"forecast":[],"lat":"14.50","lng":"150.40","movedirection":"西北西","movespeed":"23","power":"11","pressure":"975","radius10":"50","radius7":"150","speed":"30","strong":"强热带风暴","time":"2004\/8\/21 20:00:00"},{"forecast":[],"lat":"14.20","lng":"150.10","movedirection":"西","movespeed":"30","power":"11","pressure":"975","radius10":"110","radius7":"440","speed":"30","strong":"强热带风暴","time":"2004\/8\/21 21:00:00"},{"forecast":[],"lat":"14.30","lng":"149.40","movedirection":"西","movespeed":"25","power":"11","pressure":"975","radius10":"110","radius7":"440","speed":"30","strong":"强热带风暴","time":"2004\/8\/22 0:00:00"},{"forecast":[],"lat":"14.40","lng":"148.60","movedirection":"西北西","movespeed":"22","power":"13","pressure":"960","radius10":"50","radius7":"150","speed":"38","strong":"台风","time":"2004\/8\/22 2:00:00"},{"forecast":[],"lat":"14.30","lng":"148.50","movedirection":"西","movespeed":"30","power":"13","pressure":"960","radius10":"150","radius7":"440","speed":"40","strong":"台风","time":"2004\/8\/22 3:00:00"},{"forecast":[],"lat":"14.20","lng":"147.70","movedirection":"西","movespeed":"30","power":"13","pressure":"960","radius10":"150","radius7":"440","speed":"40","strong":"台风","time":"2004\/8\/22 6:00:00"},{"forecast":[],"lat":"14.10","lng":"147.60","movedirection":"西北西","movespeed":"21","power":"13","pressure":"960","radius10":"50","radius7":"150","speed":"38","strong":"台风","time":"2004\/8\/22 8:00:00"},{"forecast":[],"lat":"14.10","lng":"147.60","movedirection":"西","movespeed":"15","power":"13","pressure":"960","radius10":"150","radius7":"440","speed":"40","strong":"台风","time":"2004\/8\/22 9:00:00"},{"forecast":[],"lat":"14.10","lng":"147.10","movedirection":"西","movespeed":"9","power":"13","pressure":"960","radius10":"150","radius7":"440","speed":"40","strong":"台风","time":"2004\/8\/22 12:00:00"},{"forecast":[],"lat":"14.30","lng":"146.30","movedirection":"西北西","movespeed":"21","power":"13","pressure":"955","radius10":"80","radius7":"200","speed":"40","strong":"台风","time":"2004\/8\/22 14:00:00"},{"forecast":[],"lat":"14.40","lng":"146.40","movedirection":"西","movespeed":"20","power":"13","pressure":"950","radius10":"190","radius7":"440","speed":"40","strong":"台风","time":"2004\/8\/22 15:00:00"},{"forecast":[],"lat":"14.30","lng":"145.70","movedirection":"西","movespeed":"25","power":"14","pressure":"945","radius10":"200","radius7":"480","speed":"45","strong":"强台风","time":"2004\/8\/22 18:00:00"},{"forecast":[],"lat":"14.40","lng":"145.50","movedirection":"西北西","movespeed":"21","power":"14","pressure":"940","radius10":"100","radius7":"250","speed":"45","strong":"强台风","time":"2004\/8\/22 20:00:00"},{"forecast":[],"lat":"14.40","lng":"145.60","movedirection":"西","movespeed":"15","power":"15","pressure":"930","radius10":"240","radius7":"560","speed":"50","strong":"强台风","time":"2004\/8\/22 21:00:00"},{"forecast":[],"lat":"14.40","lng":"145.20","movedirection":"西","movespeed":"10","power":"15","pressure":"930","radius10":"240","radius7":"560","speed":"50","strong":"强台风","time":"2004\/8\/23 0:00:00"},{"forecast":[],"lat":"14.90","lng":"144.80","movedirection":"西北西","movespeed":"22","power":"16","pressure":"925","radius10":"100","radius7":"250","speed":"51","strong":"超强台风","time":"2004\/8\/23 2:00:00"},{"forecast":[],"lat":"14.90","lng":"144.80","movedirection":"西北西","movespeed":"15","power":"16","pressure":"920","radius10":"260","radius7":"600","speed":"55","strong":"超强台风","time":"2004\/8\/23 3:00:00"},{"forecast":[],"lat":"15.10","lng":"144.10","movedirection":"西北西","movespeed":"25","power":"16","pressure":"920","radius10":"260","radius7":"600","speed":"55","strong":"超强台风","time":"2004\/8\/23 6:00:00"},{"forecast":[],"lat":"15.20","lng":"143.60","movedirection":"","movespeed":"22","power":"16","pressure":"912","radius10":"120","radius7":"300","speed":"55","strong":"超强台风","time":"2004\/8\/23 8:00:00"},{"forecast":[],"lat":"15.20","lng":"143.60","movedirection":"西","movespeed":"20","power":"16","pressure":"920","radius10":"260","radius7":"650","speed":"55","strong":"超强台风","time":"2004\/8\/23 9:00:00"},{"forecast":[],"lat":"15.40","lng":"143.10","movedirection":"西北西","movespeed":"20","power":"16","pressure":"920","radius10":"260","radius7":"650","speed":"55","strong":"超强台风","time":"2004\/8\/23 12:00:00"},{"forecast":[],"lat":"15.50","lng":"142.90","movedirection":"","movespeed":"","power":"17","pressure":"915","radius10":"","radius7":"","speed":"65","strong":"超强台风","time":"2004\/8\/23 14:00:00"},{"forecast":[],"lat":"15.50","lng":"142.90","movedirection":"西北西","movespeed":"15","power":"16","pressure":"915","radius10":"280","radius7":"650","speed":"55","strong":"超强台风","time":"2004\/8\/23 15:00:00"},{"forecast":[],"lat":"16.30","lng":"142.10","movedirection":"","movespeed":"","power":"17","pressure":"915","radius10":"","radius7":"","speed":"65","strong":"超强台风","time":"2004\/8\/23 20:00:00"},{"forecast":[],"lat":"17.00","lng":"141.10","movedirection":"","movespeed":"","power":"17","pressure":"910","radius10":"","radius7":"","speed":"65","strong":"超强台风","time":"2004\/8\/24 2:00:00"},{"forecast":[],"lat":"17.40","lng":"140.30","movedirection":"","movespeed":"","power":"17","pressure":"910","radius10":"","radius7":"","speed":"65","strong":"超强台风","time":"2004\/8\/24 8:00:00"},{"forecast":[],"lat":"17.90","lng":"139.60","movedirection":"","movespeed":"","power":"17","pressure":"910","radius10":"","radius7":"","speed":"65","strong":"超强台风","time":"2004\/8\/24 14:00:00"},{"forecast":[],"lat":"18.50","lng":"139.00","movedirection":"","movespeed":"","power":"17","pressure":"910","radius10":"","radius7":"","speed":"65","strong":"超强台风","time":"2004\/8\/24 20:00:00"},{"forecast":[],"lat":"19.40","lng":"138.70","movedirection":"","movespeed":"","power":"17","pressure":"910","radius10":"","radius7":"","speed":"65","strong":"超强台风","time":"2004\/8\/25 2:00:00"},{"forecast":[],"lat":"20.30","lng":"138.20","movedirection":"","movespeed":"","power":"17","pressure":"910","radius10":"","radius7":"","speed":"65","strong":"超强台风","time":"2004\/8\/25 8:00:00"},{"forecast":[],"lat":"21.10","lng":"137.50","movedirection":"","movespeed":"","power":"17","pressure":"910","radius10":"","radius7":"","speed":"65","strong":"超强台风","time":"2004\/8\/25 14:00:00"},{"forecast":[],"lat":"21.90","lng":"137.10","movedirection":"","movespeed":"","power":"17","pressure":"910","radius10":"","radius7":"","speed":"65","strong":"超强台风","time":"2004\/8\/25 20:00:00"},{"forecast":[],"lat":"22.50","lng":"136.70","movedirection":"","movespeed":"","power":"17","pressure":"910","radius10":"","radius7":"","speed":"65","strong":"超强台风","time":"2004\/8\/26 2:00:00"},{"forecast":[],"lat":"23.40","lng":"136.30","movedirection":"","movespeed":"","power":"17","pressure":"910","radius10":"","radius7":"","speed":"65","strong":"超强台风","time":"2004\/8\/26 8:00:00"},{"forecast":[],"lat":"24.20","lng":"135.60","movedirection":"","movespeed":"","power":"17","pressure":"910","radius10":"","radius7":"","speed":"65","strong":"超强台风","time":"2004\/8\/26 14:00:00"},{"forecast":[],"lat":"24.70","lng":"135.30","movedirection":"","movespeed":"","power":"17","pressure":"920","radius10":"","radius7":"","speed":"60","strong":"超强台风","time":"2004\/8\/26 20:00:00"},{"forecast":[],"lat":"25.40","lng":"135.20","movedirection":"","movespeed":"","power":"17","pressure":"920","radius10":"","radius7":"","speed":"60","strong":"超强台风","time":"2004\/8\/27 2:00:00"},{"forecast":[],"lat":"26.00","lng":"135.10","movedirection":"","movespeed":"","power":"16","pressure":"930","radius10":"","radius7":"","speed":"55","strong":"超强台风","time":"2004\/8\/27 8:00:00"},{"forecast":[],"lat":"26.50","lng":"134.50","movedirection":"","movespeed":"","power":"16","pressure":"930","radius10":"","radius7":"","speed":"55","strong":"超强台风","time":"2004\/8\/27 14:00:00"},{"forecast":[],"lat":"26.70","lng":"134.30","movedirection":"","movespeed":"","power":"16","pressure":"930","radius10":"","radius7":"","speed":"55","strong":"超强台风","time":"2004\/8\/27 20:00:00"},{"forecast":[],"lat":"27.00","lng":"134.30","movedirection":"","movespeed":"","power":"16","pressure":"930","radius10":"","radius7":"","speed":"55","strong":"超强台风","time":"2004\/8\/28 2:00:00"},{"forecast":[],"lat":"27.10","lng":"133.90","movedirection":"","movespeed":"","power":"15","pressure":"940","radius10":"","radius7":"","speed":"50","strong":"强台风","time":"2004\/8\/28 8:00:00"},{"forecast":[],"lat":"27.30","lng":"133.60","movedirection":"","movespeed":"","power":"15","pressure":"940","radius10":"","radius7":"","speed":"50","strong":"强台风","time":"2004\/8\/28 14:00:00"},{"forecast":[],"lat":"27.60","lng":"132.90","movedirection":"","movespeed":"","power":"15","pressure":"940","radius10":"","radius7":"","speed":"50","strong":"强台风","time":"2004\/8\/28 20:00:00"},{"forecast":[],"lat":"27.70","lng":"132.10","movedirection":"","movespeed":"","power":"15","pressure":"940","radius10":"","radius7":"","speed":"50","strong":"强台风","time":"2004\/8\/29 2:00:00"},{"forecast":[],"lat":"28.00","lng":"131.80","movedirection":"","movespeed":"","power":"15","pressure":"940","radius10":"","radius7":"","speed":"50","strong":"强台风","time":"2004\/8\/29 5:00:00"},{"forecast":[],"lat":"28.20","lng":"131.30","movedirection":"","movespeed":"","power":"15","pressure":"940","radius10":"","radius7":"","speed":"50","strong":"强台风","time":"2004\/8\/29 8:00:00"},{"forecast":[],"lat":"28.70","lng":"130.90","movedirection":"","movespeed":"","power":"15","pressure":"940","radius10":"","radius7":"","speed":"50","strong":"强台风","time":"2004\/8\/29 11:00:00"},{"forecast":[],"lat":"28.80","lng":"130.40","movedirection":"","movespeed":"","power":"15","pressure":"940","radius10":"","radius7":"","speed":"50","strong":"强台风","time":"2004\/8\/29 14:00:00"},{"forecast":[],"lat":"29.20","lng":"130.10","movedirection":"","movespeed":"","power":"15","pressure":"940","radius10":"","radius7":"","speed":"50","strong":"强台风","time":"2004\/8\/29 17:00:00"},{"forecast":[],"lat":"29.40","lng":"130.00","movedirection":"","movespeed":"","power":"14","pressure":"950","radius10":"","radius7":"","speed":"45","strong":"强台风","time":"2004\/8\/29 20:00:00"},{"forecast":[],"lat":"29.80","lng":"129.80","movedirection":"","movespeed":"","power":"14","pressure":"950","radius10":"","radius7":"","speed":"45","strong":"强台风","time":"2004\/8\/29 23:00:00"},{"forecast":[],"lat":"30.20","lng":"129.80","movedirection":"","movespeed":"","power":"14","pressure":"950","radius10":"","radius7":"","speed":"45","strong":"强台风","time":"2004\/8\/30 2:00:00"},{"forecast":[],"lat":"30.90","lng":"130.00","movedirection":"","movespeed":"","power":"14","pressure":"950","radius10":"","radius7":"","speed":"45","strong":"强台风","time":"2004\/8\/30 5:00:00"},{"forecast":[],"lat":"31.40","lng":"130.20","movedirection":"","movespeed":"","power":"13","pressure":"955","radius10":"","radius7":"","speed":"40","strong":"台风","time":"2004\/8\/30 8:00:00"},{"forecast":[],"lat":"32.50","lng":"130.70","movedirection":"","movespeed":"","power":"13","pressure":"960","radius10":"","radius7":"","speed":"40","strong":"台风","time":"2004\/8\/30 11:00:00"},{"forecast":[],"lat":"33.60","lng":"131.10","movedirection":"","movespeed":"","power":"13","pressure":"965","radius10":"","radius7":"","speed":"40","strong":"台风","time":"2004\/8\/30 14:00:00"},{"forecast":[],"lat":"34.10","lng":"131.80","movedirection":"","movespeed":"","power":"12","pressure":"970","radius10":"","radius7":"","speed":"35","strong":"台风","time":"2004\/8\/30 17:00:00"},{"forecast":[],"lat":"34.90","lng":"133.10","movedirection":"","movespeed":"","power":"12","pressure":"975","radius10":"","radius7":"","speed":"33","strong":"台风","time":"2004\/8\/30 20:00:00"},{"forecast":[],"lat":"46.70","lng":"145.70","movedirection":"","movespeed":"","power":"9","pressure":"975","radius10":"","radius7":"","speed":"23","strong":"热带风暴","time":"2004\/8\/31 20:00:00"}],"starttime":"2004\/8\/20 14:00:00","tfid":"200417","warnlevel":"6"}]
