[{"centerlat":"24.550000","centerlng":"126.750000","endtime":"2004\/8\/26 11:00:00","enname":"AERE","isactive":"0","land":[],"name":"艾利","points":[{"forecast":[],"lat":"13.60","lng":"135.10","movedirection":"","movespeed":"12","power":"8","pressure":"998","radius10":"","radius7":"","speed":"18","strong":"热带风暴","time":"2004\/8\/20 8:00:00"},{"forecast":[],"lat":"15.20","lng":"136.20","movedirection":"西北","movespeed":"15","power":"9","pressure":"995","radius10":"","radius7":"150","speed":"23","strong":"热带风暴","time":"2004\/8\/20 14:00:00"},{"forecast":[],"lat":"15.60","lng":"135.50","movedirection":"","movespeed":"","power":"9","pressure":"","radius10":"","radius7":"","speed":"23","strong":"热带风暴","time":"2004\/8\/20 20:00:00"},{"forecast":[],"lat":"16.20","lng":"135.00","movedirection":"","movespeed":"16","power":"9","pressure":"990","radius10":"","radius7":"150","speed":"23","strong":"热带风暴","time":"2004\/8\/21 2:00:00"},{"forecast":[],"lat":"17.50","lng":"134.00","movedirection":"西北","movespeed":"16","power":"10","pressure":"985","radius10":"","radius7":"150","speed":"25","strong":"强热带风暴","time":"2004\/8\/21 8:00:00"},{"forecast":[],"lat":"18.20","lng":"132.90","movedirection":"西北","movespeed":"18","power":"11","pressure":"980","radius10":"50","radius7":"150","speed":"30","strong":"强热带风暴","time":"2004\/8\/21 14:00:00"},{"forecast":[],"lat":"19.10","lng":"131.90","movedirection":"西北","movespeed":"18","power":"12","pressure":"980","radius10":"50","radius7":"150","speed":"33","strong":"台风","time":"2004\/8\/21 20:00:00"},{"forecast":[],"lat":"19.70","lng":"130.80","movedirection":"西北","movespeed":"17","power":"12","pressure":"975","radius10":"50","radius7":"150","speed":"35","strong":"台风","time":"2004\/8\/22 2:00:00"},{"forecast":[],"lat":"20.10","lng":"130.10","movedirection":"西","movespeed":"25","power":"12","pressure":"975","radius10":"600","radius7":"520","speed":"35","strong":"台风","time":"2004\/8\/22 5:00:00"},{"forecast":[],"lat":"20.20","lng":"129.80","movedirection":"西北","movespeed":"17","power":"12","pressure":"975","radius10":"50","radius7":"150","speed":"35","strong":"台风","time":"2004\/8\/22 8:00:00"},{"forecast":[],"lat":"20.40","lng":"129.50","movedirection":"北西","movespeed":"15","power":"12","pressure":"975","radius10":"110","radius7":"520","speed":"35","strong":"台风","time":"2004\/8\/22 11:00:00"},{"forecast":[],"lat":"20.70","lng":"128.90","movedirection":"北西","movespeed":"20","power":"12","pressure":"975","radius10":"110","radius7":"520","speed":"35","strong":"台风","time":"2004\/8\/22 14:00:00"},{"forecast":[],"lat":"21.30","lng":"128.30","movedirection":"西北西","movespeed":"20","power":"12","pressure":"970","radius10":"130","radius7":"520","speed":"35","strong":"台风","time":"2004\/8\/22 17:00:00"},{"forecast":[],"lat":"21.40","lng":"128.00","movedirection":"北西","movespeed":"25","power":"12","pressure":"975","radius10":"110","radius7":"520","speed":"35","strong":"台风","time":"2004\/8\/22 20:00:00"},{"forecast":[],"lat":"22.30","lng":"127.10","movedirection":"北西","movespeed":"20","power":"12","pressure":"970","radius10":"130","radius7":"520","speed":"35","strong":"台风","time":"2004\/8\/23 2:00:00"},{"forecast":[],"lat":"22.70","lng":"126.60","movedirection":"北西","movespeed":"15","power":"12","pressure":"970","radius10":"130","radius7":"520","speed":"35","strong":"台风","time":"2004\/8\/23 5:00:00"},{"forecast":[],"lat":"22.90","lng":"126.30","movedirection":"北西","movespeed":"20","power":"12","pressure":"970","radius10":"130","radius7":"520","speed":"35","strong":"台风","time":"2004\/8\/23 8:00:00"},{"forecast":[],"lat":"23.20","lng":"125.70","movedirection":"西北西","movespeed":"20","power":"12","pressure":"970","radius10":"130","radius7":"520","speed":"35","strong":"台风","time":"2004\/8\/23 11:00:00"},{"forecast":[],"lat":"23.50","lng":"125.50","movedirection":"西北西","movespeed":"20","power":"13","pressure":"970","radius10":"150","radius7":"500","speed":"40","strong":"台风","time":"2004\/8\/23 14:00:00"},{"forecast":[],"lat":"23.70","lng":"125.10","movedirection":"","movespeed":"","power":"13","pressure":"960","radius10":"","radius7":"","speed":"40","strong":"台风","time":"2004\/8\/23 17:00:00"},{"forecast":[],"lat":"23.80","lng":"125.00","movedirection":"","movespeed":"","power":"","pressure":"","radius10":"","radius7":"","speed":"","strong":"","time":"2004\/8\/23 20:00:00"},{"forecast":[],"lat":"24.00","lng":"124.70","movedirection":"","movespeed":"","power":"13","pressure":"960","radius10":"","radius7":"","speed":"40","strong":"台风","time":"2004\/8\/23 23:00:00"},{"forecast":[],"lat":"24.60","lng":"124.30","movedirection":"","movespeed":"","power":"13","pressure":"960","radius10":"","radius7":"","speed":"40","strong":"台风","time":"2004\/8\/24 2:00:00"},{"forecast":[],"lat":"25.00","lng":"123.80","movedirection":"","movespeed":"","power":"13","pressure":"960","radius10":"","radius7":"","speed":"40","strong":"台风","time":"2004\/8\/24 5:00:00"},{"forecast":[],"lat":"25.00","lng":"123.70","movedirection":"","movespeed":"12","power":"13","pressure":"960","radius10":"180","radius7":"500","speed":"40","strong":"台风","time":"2004\/8\/24 8:00:00"},{"forecast":[],"lat":"25.10","lng":"123.60","movedirection":"","movespeed":"","power":"13","pressure":"960","radius10":"","radius7":"","speed":"40","strong":"台风","time":"2004\/8\/24 11:00:00"},{"forecast":[],"lat":"25.20","lng":"123.50","movedirection":"西北西","movespeed":"14","power":"13","pressure":"960","radius10":"180","radius7":"500","speed":"40","strong":"台风","time":"2004\/8\/24 14:00:00"},{"forecast":[],"lat":"25.40","lng":"123.40","movedirection":"西北西","movespeed":"14","power":"13","pressure":"960","radius10":"180","radius7":"500","speed":"40","strong":"台风","time":"2004\/8\/24 17:00:00"},{"forecast":[],"lat":"25.40","lng":"123.10","movedirection":"西北西","movespeed":"14","power":"13","pressure":"960","radius10":"180","radius7":"500","speed":"40","strong":"台风","time":"2004\/8\/24 20:00:00"},{"forecast":[],"lat":"25.50","lng":"122.80","movedirection":"西","movespeed":"","power":"13","pressure":"960","radius10":"180","radius7":"500","speed":"40","strong":"台风","time":"2004\/8\/24 23:00:00"},{"forecast":[],"lat":"25.50","lng":"122.10","movedirection":"","movespeed":"","power":"13","pressure":"960","radius10":"180","radius7":"500","speed":"40","strong":"台风","time":"2004\/8\/25 2:00:00"},{"forecast":[],"lat":"25.40","lng":"121.80","movedirection":"","movespeed":"","power":"13","pressure":"960","radius10":"180","radius7":"500","speed":"40","strong":"台风","time":"2004\/8\/25 5:00:00"},{"forecast":[],"lat":"25.40","lng":"121.50","movedirection":"西","movespeed":"16","power":"13","pressure":"960","radius10":"180","radius7":"500","speed":"40","strong":"台风","time":"2004\/8\/25 8:00:00"},{"forecast":[],"lat":"25.50","lng":"121.00","movedirection":"西","movespeed":"","power":"13","pressure":"960","radius10":"180","radius7":"500","speed":"40","strong":"台风","time":"2004\/8\/25 11:00:00"},{"forecast":[],"lat":"25.40","lng":"120.30","movedirection":"西","movespeed":"","power":"13","pressure":"960","radius10":"","radius7":"","speed":"40","strong":"台风","time":"2004\/8\/25 14:00:00"},{"forecast":[],"lat":"25.40","lng":"119.60","movedirection":"","movespeed":"","power":"12","pressure":"970","radius10":"150","radius7":"500","speed":"35","strong":"台风","time":"2004\/8\/25 17:00:00"},{"forecast":[],"lat":"25.10","lng":"119.10","movedirection":"","movespeed":"14","power":"12","pressure":"970","radius10":"150","radius7":"450","speed":"33","strong":"台风","time":"2004\/8\/25 20:00:00"},{"forecast":[],"lat":"24.60","lng":"118.60","movedirection":"","movespeed":"","power":"12","pressure":"970","radius10":"","radius7":"","speed":"33","strong":"台风","time":"2004\/8\/25 23:00:00"},{"forecast":[],"lat":"24.30","lng":"117.90","movedirection":"","movespeed":"12","power":"11","pressure":"975","radius10":"","radius7":"","speed":"30","strong":"强热带风暴","time":"2004\/8\/26 2:00:00"},{"forecast":[],"lat":"24.00","lng":"117.60","movedirection":"","movespeed":"12","power":"10","pressure":"980","radius10":"","radius7":"","speed":"25","strong":"强热带风暴","time":"2004\/8\/26 5:00:00"},{"forecast":[],"lat":"23.80","lng":"117.70","movedirection":"","movespeed":"","power":"9","pressure":"985","radius10":"","radius7":"","speed":"23","strong":"热带风暴","time":"2004\/8\/26 8:00:00"},{"forecast":[],"lat":"23.60","lng":"117.30","movedirection":"","movespeed":"","power":"8","pressure":"985","radius10":"","radius7":"","speed":"20","strong":"热带风暴","time":"2004\/8\/26 11:00:00"}],"starttime":"2004\/8\/20 8:00:00","tfid":"200418","warnlevel":"4"}]
