[{"centerlat":"25.900000","centerlng":"120.650000","endtime":"1984\/8\/31 0:00:00","enname":"JUNE","isactive":"0","land":[],"name":"裘恩","points":[{"forecast":[],"lat":"17.70","lng":"125.30","movedirection":"","movespeed":"","power":"9","pressure":"","radius10":"","radius7":"","speed":"23","strong":"热带风暴","time":"1984\/8\/28 0:00:00"},{"forecast":[],"lat":"17.90","lng":"124.20","movedirection":"","movespeed":"","power":"9","pressure":"","radius10":"","radius7":"","speed":"23","strong":"热带风暴","time":"1984\/8\/28 6:00:00"},{"forecast":[],"lat":"17.90","lng":"122.90","movedirection":"","movespeed":"","power":"10","pressure":"","radius10":"","radius7":"","speed":"28","strong":"强热带风暴","time":"1984\/8\/28 12:00:00"},{"forecast":[],"lat":"18.20","lng":"121.60","movedirection":"","movespeed":"","power":"9","pressure":"","radius10":"","radius7":"","speed":"23","strong":"热带风暴","time":"1984\/8\/28 18:00:00"},{"forecast":[],"lat":"18.60","lng":"120.60","movedirection":"","movespeed":"","power":"9","pressure":"","radius10":"","radius7":"","speed":"23","strong":"热带风暴","time":"1984\/8\/29 0:00:00"},{"forecast":[],"lat":"18.70","lng":"119.60","movedirection":"","movespeed":"","power":"10","pressure":"","radius10":"","radius7":"","speed":"25","strong":"强热带风暴","time":"1984\/8\/29 6:00:00"},{"forecast":[],"lat":"18.90","lng":"119.00","movedirection":"","movespeed":"","power":"10","pressure":"","radius10":"","radius7":"","speed":"25","strong":"强热带风暴","time":"1984\/8\/29 12:00:00"},{"forecast":[],"lat":"19.60","lng":"118.70","movedirection":"","movespeed":"","power":"10","pressure":"","radius10":"","radius7":"","speed":"28","strong":"强热带风暴","time":"1984\/8\/29 18:00:00"},{"forecast":[],"lat":"20.40","lng":"118.40","movedirection":"","movespeed":"","power":"11","pressure":"","radius10":"","radius7":"","speed":"30","strong":"强热带风暴","time":"1984\/8\/30 0:00:00"},{"forecast":[],"lat":"21.10","lng":"117.40","movedirection":"","movespeed":"","power":"11","pressure":"","radius10":"","radius7":"","speed":"30","strong":"强热带风暴","time":"1984\/8\/30 6:00:00"},{"forecast":[],"lat":"21.90","lng":"116.60","movedirection":"","movespeed":"","power":"11","pressure":"","radius10":"","radius7":"","speed":"30","strong":"强热带风暴","time":"1984\/8\/30 12:00:00"},{"forecast":[],"lat":"23.10","lng":"116.40","movedirection":"","movespeed":"","power":"9","pressure":"","radius10":"","radius7":"","speed":"23","strong":"热带风暴","time":"1984\/8\/30 18:00:00"},{"forecast":[],"lat":"24.10","lng":"116.00","movedirection":"","movespeed":"","power":"6","pressure":"","radius10":"","radius7":"","speed":"12","strong":"热带低压","time":"1984\/8\/31 0:00:00"}],"starttime":"1984\/8\/28 0:00:00","tfid":"198411","warnlevel":"3"}]
