[{"centerlat":"29.650000","centerlng":"121.450000","endtime":"2003\/8\/20 18:00:00","enname":"VAMCO","isactive":"0","land":[],"name":"环高","points":[{"forecast":[],"lat":"18.80","lng":"125.20","movedirection":"","movespeed":"","power":"5","pressure":"1004","radius10":"","radius7":"","speed":"10","strong":"热带低压","time":"2003\/8\/18 18:00:00"},{"forecast":[],"lat":"20.80","lng":"125.40","movedirection":"","movespeed":"","power":"6","pressure":"1002","radius10":"","radius7":"","speed":"12","strong":"热带低压","time":"2003\/8\/19 0:00:00"},{"forecast":[],"lat":"22.80","lng":"124.80","movedirection":"","movespeed":"","power":"7","pressure":"1000","radius10":"","radius7":"","speed":"15","strong":"热带低压","time":"2003\/8\/19 6:00:00"},{"forecast":[],"lat":"24.30","lng":"123.40","movedirection":"","movespeed":"","power":"7","pressure":"1000","radius10":"","radius7":"","speed":"15","strong":"热带低压","time":"2003\/8\/19 12:00:00"},{"forecast":[],"lat":"25.80","lng":"122.20","movedirection":"","movespeed":"","power":"7","pressure":"997","radius10":"","radius7":"","speed":"17","strong":"热带低压","time":"2003\/8\/19 18:00:00"},{"forecast":[],"lat":"27.20","lng":"120.90","movedirection":"","movespeed":"","power":"7","pressure":"997","radius10":"","radius7":"","speed":"17","strong":"热带低压","time":"2003\/8\/20 0:00:00"},{"forecast":[],"lat":"28.30","lng":"119.50","movedirection":"","movespeed":"","power":"6","pressure":"1002","radius10":"","radius7":"","speed":"12","strong":"热带低压","time":"2003\/8\/20 6:00:00"},{"forecast":[],"lat":"29.80","lng":"118.30","movedirection":"","movespeed":"","power":"5","pressure":"1004","radius10":"","radius7":"","speed":"10","strong":"热带低压","time":"2003\/8\/20 12:00:00"},{"forecast":[],"lat":"30.50","lng":"117.50","movedirection":"","movespeed":"","power":"5","pressure":"1004","radius10":"","radius7":"","speed":"10","strong":"热带低压","time":"2003\/8\/20 18:00:00"}],"starttime":"2003\/8\/18 18:00:00","tfid":"200311","warnlevel":"1"}]
