[{"centerlat":"22.750000","centerlng":"109.050000","endtime":"1966\/8\/2 18:00:00","enname":"PHYLLIS","isactive":"0","land":[],"name":"费利斯","points":[{"forecast":[],"lat":"15.30","lng":"112.00","movedirection":"","movespeed":"","power":"6","pressure":"","radius10":"","radius7":"","speed":"12","strong":"热带低压","time":"1966\/7\/31 18:00:00"},{"forecast":[],"lat":"16.10","lng":"111.20","movedirection":"","movespeed":"","power":"6","pressure":"","radius10":"","radius7":"","speed":"12","strong":"热带低压","time":"1966\/8\/1 0:00:00"},{"forecast":[],"lat":"16.80","lng":"110.50","movedirection":"","movespeed":"","power":"7","pressure":"","radius10":"","radius7":"","speed":"15","strong":"热带低压","time":"1966\/8\/1 6:00:00"},{"forecast":[],"lat":"17.60","lng":"109.90","movedirection":"","movespeed":"","power":"7","pressure":"","radius10":"","radius7":"","speed":"17","strong":"热带低压","time":"1966\/8\/1 12:00:00"},{"forecast":[],"lat":"18.40","lng":"109.20","movedirection":"","movespeed":"","power":"7","pressure":"","radius10":"","radius7":"","speed":"17","strong":"热带低压","time":"1966\/8\/1 18:00:00"},{"forecast":[],"lat":"18.70","lng":"108.20","movedirection":"","movespeed":"","power":"7","pressure":"","radius10":"","radius7":"","speed":"17","strong":"热带低压","time":"1966\/8\/2 0:00:00"},{"forecast":[],"lat":"19.00","lng":"107.20","movedirection":"","movespeed":"","power":"8","pressure":"","radius10":"","radius7":"","speed":"20","strong":"热带风暴","time":"1966\/8\/2 6:00:00"},{"forecast":[],"lat":"19.30","lng":"106.70","movedirection":"","movespeed":"","power":"9","pressure":"","radius10":"","radius7":"","speed":"23","strong":"热带风暴","time":"1966\/8\/2 12:00:00"},{"forecast":[],"lat":"20.20","lng":"106.10","movedirection":"","movespeed":"","power":"7","pressure":"","radius10":"","radius7":"","speed":"15","strong":"热带低压","time":"1966\/8\/2 18:00:00"}],"starttime":"1966\/7\/31 18:00:00","tfid":"196609","warnlevel":"2"}]
