[{"centerlat":"23.300000","centerlng":"118.850000","endtime":"1980\/7\/19 6:00:00","enname":"-","isactive":"0","land":[],"name":"-","points":[{"forecast":[],"lat":"14.00","lng":"125.40","movedirection":"","movespeed":"","power":"5","pressure":"","radius10":"","radius7":"","speed":"10","strong":"热带低压","time":"1980\/7\/15 18:00:00"},{"forecast":[],"lat":"14.00","lng":"123.90","movedirection":"","movespeed":"","power":"5","pressure":"","radius10":"","radius7":"","speed":"10","strong":"热带低压","time":"1980\/7\/16 0:00:00"},{"forecast":[],"lat":"14.20","lng":"122.20","movedirection":"","movespeed":"","power":"5","pressure":"","radius10":"","radius7":"","speed":"10","strong":"热带低压","time":"1980\/7\/16 6:00:00"},{"forecast":[],"lat":"14.40","lng":"120.80","movedirection":"","movespeed":"","power":"6","pressure":"","radius10":"","radius7":"","speed":"12","strong":"热带低压","time":"1980\/7\/16 12:00:00"},{"forecast":[],"lat":"14.70","lng":"119.20","movedirection":"","movespeed":"","power":"6","pressure":"","radius10":"","radius7":"","speed":"12","strong":"热带低压","time":"1980\/7\/16 18:00:00"},{"forecast":[],"lat":"15.20","lng":"117.80","movedirection":"","movespeed":"","power":"7","pressure":"","radius10":"","radius7":"","speed":"15","strong":"热带低压","time":"1980\/7\/17 0:00:00"},{"forecast":[],"lat":"16.00","lng":"116.30","movedirection":"","movespeed":"","power":"7","pressure":"","radius10":"","radius7":"","speed":"15","strong":"热带低压","time":"1980\/7\/17 6:00:00"},{"forecast":[],"lat":"17.20","lng":"115.20","movedirection":"","movespeed":"","power":"7","pressure":"","radius10":"","radius7":"","speed":"15","strong":"热带低压","time":"1980\/7\/17 12:00:00"},{"forecast":[],"lat":"18.30","lng":"114.40","movedirection":"","movespeed":"","power":"7","pressure":"","radius10":"","radius7":"","speed":"15","strong":"热带低压","time":"1980\/7\/17 18:00:00"},{"forecast":[],"lat":"19.10","lng":"113.90","movedirection":"","movespeed":"","power":"7","pressure":"","radius10":"","radius7":"","speed":"15","strong":"热带低压","time":"1980\/7\/18 0:00:00"},{"forecast":[],"lat":"19.90","lng":"113.50","movedirection":"","movespeed":"","power":"7","pressure":"","radius10":"","radius7":"","speed":"15","strong":"热带低压","time":"1980\/7\/18 6:00:00"},{"forecast":[],"lat":"20.70","lng":"113.00","movedirection":"","movespeed":"","power":"7","pressure":"","radius10":"","radius7":"","speed":"15","strong":"热带低压","time":"1980\/7\/18 12:00:00"},{"forecast":[],"lat":"21.30","lng":"112.80","movedirection":"","movespeed":"","power":"7","pressure":"","radius10":"","radius7":"","speed":"15","strong":"热带低压","time":"1980\/7\/18 18:00:00"},{"forecast":[],"lat":"21.80","lng":"112.50","movedirection":"","movespeed":"","power":"7","pressure":"","radius10":"","radius7":"","speed":"15","strong":"热带低压","time":"1980\/7\/19 0:00:00"},{"forecast":[],"lat":"22.60","lng":"112.30","movedirection":"","movespeed":"","power":"5","pressure":"","radius10":"","radius7":"","speed":"10","strong":"热带低压","time":"1980\/7\/19 6:00:00"}],"starttime":"1980\/7\/15 18:00:00","tfid":"198008","warnlevel":"1"}]
